TQS/TQSBuild.py
TQS/TQSDwg.py
TQS/TQSEag.py
TQS/TQSExec.py
TQS/TQSGeo.py
TQS/TQSGrid.py
TQS/TQSJan.py
TQS/TQSModel.py
TQS/TQSUtil.py
TQS/__init__.py
pytqs/__init__.py
pytqs/building_tree.py
pytqs/cpl_tree.py
pytqs/drawning.py
pytqs/eag_utils.py
pytqs/elements.py
pytqs/project.py
pytqs/rebar.py
pytqs-2.1.0.dist-info/METADATA
pytqs-2.1.0.dist-info/WHEEL
pytqs-2.1.0.dist-info/top_level.txt
pytqs-2.1.0.dist-info/RECORD
