Metadata-Version: 2.4
Name: pytqs
Version: 2.1.0
Summary: Bibliteca para facilitar a integração do Python com o TQS
Home-page: https://github.com/leonardopbatista/pytqs
Author: Leonardo Pires Batista
Author-email: leonardopbatista98@gmail.com
Project-URL: Código fonte, https://github.com/leonardopbatista/pytqs
Project-URL: Download, https://github.com/leonardopbatista/pytqs
Keywords: tqs python
Requires-Python: >=3.12
Requires-Dist: pygeometry2d==1.2.0
Dynamic: author
Dynamic: author-email
Dynamic: description
Dynamic: description-content-type
Dynamic: home-page
Dynamic: keywords
Dynamic: project-url
Dynamic: requires-dist
Dynamic: requires-python
Dynamic: summary
